zltk/__init__.py
zltk/zltk.py
zltk-0.0.1.dist-info/LICENSE
zltk-0.0.1.dist-info/METADATA
zltk-0.0.1.dist-info/WHEEL
zltk-0.0.1.dist-info/top_level.txt
zltk-0.0.1.dist-info/RECORD
