Metadata-Version: 2.1
Name: zltk
Version: 0.0.1
Summary: A collection of commonly used functions.
Home-page: https://github.com/chengzl18/zltk
Download-URL: https://github.com/chengzl18/zltk/archive/master.zip
Author: Zhili Cheng
Author-email: chengzl22@mails.tsinghua.edu.cn
Keywords: tokenizer,Chinese
Classifier: Programming Language :: Python :: 3
Classifier: Programming Language :: Python :: 3.9
Requires-Python: >=3.6.0
License-File: LICENSE
Requires-Dist: pyyaml
Requires-Dist: numpy
Requires-Dist: huggingface-hub
